{
  "canal": "salao",
  "canal_nome": "Salão",
  "data_geracao": "2026-02-28T00:52:10.905284",
  "dados_lojas": [
    {
      "loja_id": 12,
      "analises": {
        "2024-06": {
          "faturamento": 15410.209999999992,
          "quantidade": 81,
          "produtos": 81
        },
        "2024-07": {
          "faturamento": 22227.510000000028,
          "quantidade": 98,
          "produtos": 98
        },
        "2024-08": {
          "faturamento": 23950.07000000001,
          "quantidade": 88,
          "produtos": 88
        },
        "2024-09": {
          "faturamento": 26877.810000000027,
          "quantidade": 94,
          "produtos": 94
        },
        "2024-10": {
          "faturamento": 32987.720000000016,
          "quantidade": 91,
          "produtos": 91
        },
        "2024-11": {
          "faturamento": 32323.69000000001,
          "quantidade": 102,
          "produtos": 102
        },
        "2024-12": {
          "faturamento": 35544.43000000002,
          "quantidade": 100,
          "produtos": 100
        },
        "2025-01": {
          "faturamento": 35383.68000000004,
          "quantidade": 105,
          "produtos": 105
        },
        "2025-02": {
          "faturamento": 28162.710000000043,
          "quantidade": 103,
          "produtos": 103
        },
        "2025-03": {
          "faturamento": 30095.870000000043,
          "quantidade": 111,
          "produtos": 111
        },
        "2025-04": {
          "faturamento": 19701.54000000003,
          "quantidade": 110,
          "produtos": 110
        },
        "2025-05": {
          "faturamento": 21270.000000000015,
          "quantidade": 98,
          "produtos": 98
        },
        "2025-06": {
          "faturamento": 29058.97000000001,
          "quantidade": 109,
          "produtos": 109
        },
        "2025-07": {
          "faturamento": 25322.73,
          "quantidade": 97,
          "produtos": 97
        },
        "2025-08": {
          "faturamento": 22754.320000000018,
          "quantidade": 93,
          "produtos": 93
        },
        "2025-09": {
          "faturamento": 19977.380000000026,
          "quantidade": 92,
          "produtos": 92
        },
        "2025-10": {
          "faturamento": 26712.750000000022,
          "quantidade": 101,
          "produtos": 101
        },
        "2025-11": {
          "faturamento": 30186.520000000044,
          "quantidade": 99,
          "produtos": 99
        },
        "2025-12": {
          "faturamento": 37796.68000000004,
          "quantidade": 118,
          "produtos": 118
        },
        "2026-01": {
          "faturamento": 29042.83000000004,
          "quantidade": 137,
          "produtos": 137
        },
        "2026-02": {
          "faturamento": 15094.269999999988,
          "quantidade": 70,
          "produtos": 70
        },
        "2024-01": {
          "faturamento": 0,
          "quantidade": 0,
          "produtos": 0
        },
        "2024-02": {
          "faturamento": 0,
          "quantidade": 0,
          "produtos": 0
        },
        "2024-03": {
          "faturamento": 0,
          "quantidade": 0,
          "produtos": 0
        },
        "2024-04": {
          "faturamento": 0,
          "quantidade": 0,
          "produtos": 0
        },
        "2024-05": {
          "faturamento": 0,
          "quantidade": 0,
          "produtos": 0
        },
        "2023-12": {
          "faturamento": 0,
          "quantidade": 0,
          "produtos": 0
        }
      }
    },
    {
      "loja_id": 14,
      "analises": {
        "2024-07": {
          "faturamento": 7834.499999999997,
          "quantidade": 32,
          "produtos": 32
        },
        "2024-08": {
          "faturamento": 16969.20000000001,
          "quantidade": 42,
          "produtos": 42
        },
        "2024-09": {
          "faturamento": 18775.020000000008,
          "quantidade": 49,
          "produtos": 49
        },
        "2024-10": {
          "faturamento": 12494.599999999995,
          "quantidade": 43,
          "produtos": 43
        },
        "2024-11": {
          "faturamento": 17079.030000000002,
          "quantidade": 48,
          "produtos": 48
        },
        "2024-12": {
          "faturamento": 17852.84000000001,
          "quantidade": 49,
          "produtos": 49
        },
        "2025-01": {
          "faturamento": 16533.199999999997,
          "quantidade": 51,
          "produtos": 51
        },
        "2025-02": {
          "faturamento": 14032.549999999992,
          "quantidade": 44,
          "produtos": 44
        },
        "2025-03": {
          "faturamento": 19262.18000000001,
          "quantidade": 51,
          "produtos": 51
        },
        "2025-04": {
          "faturamento": 11844.799999999997,
          "quantidade": 41,
          "produtos": 41
        },
        "2025-05": {
          "faturamento": 12084.229999999989,
          "quantidade": 42,
          "produtos": 42
        },
        "2025-06": {
          "faturamento": 17632.160000000014,
          "quantidade": 56,
          "produtos": 56
        },
        "2025-07": {
          "faturamento": 15636.159999999996,
          "quantidade": 53,
          "produtos": 53
        },
        "2025-08": {
          "faturamento": 15670.399999999998,
          "quantidade": 49,
          "produtos": 49
        },
        "2025-09": {
          "faturamento": 14527.299999999994,
          "quantidade": 44,
          "produtos": 44
        },
        "2025-10": {
          "faturamento": 15797.699999999997,
          "quantidade": 43,
          "produtos": 43
        },
        "2025-11": {
          "faturamento": 22341.00000000001,
          "quantidade": 56,
          "produtos": 56
        },
        "2025-12": {
          "faturamento": 26086.600000000017,
          "quantidade": 70,
          "produtos": 70
        },
        "2026-01": {
          "faturamento": 33560.20000000003,
          "quantidade": 67,
          "produtos": 67
        },
        "2026-02": {
          "faturamento": 11827.59999999999,
          "quantidade": 51,
          "produtos": 51
        }
      }
    },
    {
      "loja_id": 15,
      "analises": {
        "2024-06": {
          "faturamento": 80266.95000000001,
          "quantidade": 120,
          "produtos": 120
        },
        "2024-07": {
          "faturamento": 82289.65000000002,
          "quantidade": 120,
          "produtos": 120
        },
        "2024-08": {
          "faturamento": 96279.75,
          "quantidade": 110,
          "produtos": 110
        },
        "2024-09": {
          "faturamento": 108064.25000000001,
          "quantidade": 121,
          "produtos": 121
        },
        "2024-10": {
          "faturamento": 111853.85,
          "quantidade": 117,
          "produtos": 117
        },
        "2024-11": {
          "faturamento": 127090.24999999997,
          "quantidade": 125,
          "produtos": 125
        },
        "2024-12": {
          "faturamento": 121144.14999999998,
          "quantidade": 117,
          "produtos": 117
        },
        "2025-01": {
          "faturamento": 114141.34999999999,
          "quantidade": 112,
          "produtos": 112
        },
        "2025-02": {
          "faturamento": 119498.35000000003,
          "quantidade": 117,
          "produtos": 117
        },
        "2025-03": {
          "faturamento": 139155.44999999998,
          "quantidade": 119,
          "produtos": 119
        },
        "2025-04": {
          "faturamento": 113341.35000000003,
          "quantidade": 108,
          "produtos": 108
        },
        "2025-05": {
          "faturamento": 117800.75,
          "quantidade": 111,
          "produtos": 111
        },
        "2025-06": {
          "faturamento": 124015.10000000006,
          "quantidade": 101,
          "produtos": 101
        },
        "2025-07": {
          "faturamento": 102285.55000000003,
          "quantidade": 109,
          "produtos": 109
        },
        "2025-08": {
          "faturamento": 116810.75000000001,
          "quantidade": 107,
          "produtos": 107
        },
        "2025-09": {
          "faturamento": 98353.80000000002,
          "quantidade": 111,
          "produtos": 111
        },
        "2025-10": {
          "faturamento": 94842.35000000002,
          "quantidade": 105,
          "produtos": 105
        },
        "2025-11": {
          "faturamento": 107405.29999999999,
          "quantidade": 107,
          "produtos": 107
        },
        "2025-12": {
          "faturamento": 101180.70000000003,
          "quantidade": 106,
          "produtos": 106
        },
        "2026-01": {
          "faturamento": 97801.29999999999,
          "quantidade": 109,
          "produtos": 109
        },
        "2026-02": {
          "faturamento": 19929.5,
          "quantidade": 66,
          "produtos": 66
        },
        "2023-05": {
          "faturamento": 0,
          "quantidade": 0,
          "produtos": 0
        },
        "2023-06": {
          "faturamento": 0,
          "quantidade": 0,
          "produtos": 0
        },
        "2023-07": {
          "faturamento": 0,
          "quantidade": 0,
          "produtos": 0
        },
        "2023-08": {
          "faturamento": 0,
          "quantidade": 0,
          "produtos": 0
        },
        "2023-09": {
          "faturamento": 0,
          "quantidade": 0,
          "produtos": 0
        },
        "2023-10": {
          "faturamento": 0,
          "quantidade": 0,
          "produtos": 0
        },
        "2023-11": {
          "faturamento": 0,
          "quantidade": 0,
          "produtos": 0
        },
        "2023-12": {
          "faturamento": 0,
          "quantidade": 0,
          "produtos": 0
        },
        "2024-01": {
          "faturamento": 0,
          "quantidade": 0,
          "produtos": 0
        },
        "2024-02": {
          "faturamento": 0,
          "quantidade": 0,
          "produtos": 0
        },
        "2024-03": {
          "faturamento": 0,
          "quantidade": 0,
          "produtos": 0
        },
        "2024-04": {
          "faturamento": 0,
          "quantidade": 0,
          "produtos": 0
        },
        "2024-05": {
          "faturamento": 0,
          "quantidade": 0,
          "produtos": 0
        }
      }
    },
    {
      "loja_id": 2,
      "analises": {
        "2024-06": {
          "faturamento": 17911.13000000003,
          "quantidade": 108,
          "produtos": 108
        },
        "2024-07": {
          "faturamento": 25768.260000000035,
          "quantidade": 120,
          "produtos": 120
        },
        "2024-08": {
          "faturamento": 28285.47000000004,
          "quantidade": 132,
          "produtos": 132
        },
        "2024-09": {
          "faturamento": 28209.640000000036,
          "quantidade": 151,
          "produtos": 151
        },
        "2024-10": {
          "faturamento": 29765.79000000003,
          "quantidade": 156,
          "produtos": 156
        },
        "2024-11": {
          "faturamento": 26457.34000000006,
          "quantidade": 159,
          "produtos": 159
        },
        "2024-12": {
          "faturamento": 29760.02000000007,
          "quantidade": 158,
          "produtos": 158
        },
        "2025-01": {
          "faturamento": 19205.270000000015,
          "quantidade": 121,
          "produtos": 121
        },
        "2025-02": {
          "faturamento": 23897.440000000042,
          "quantidade": 141,
          "produtos": 141
        },
        "2025-03": {
          "faturamento": 26127.210000000054,
          "quantidade": 152,
          "produtos": 152
        },
        "2025-04": {
          "faturamento": 21248.820000000043,
          "quantidade": 129,
          "produtos": 129
        },
        "2025-05": {
          "faturamento": 26373.730000000047,
          "quantidade": 137,
          "produtos": 137
        },
        "2025-06": {
          "faturamento": 27841.110000000008,
          "quantidade": 127,
          "produtos": 127
        },
        "2025-07": {
          "faturamento": 23496.520000000033,
          "quantidade": 118,
          "produtos": 118
        },
        "2025-08": {
          "faturamento": 31403.520000000048,
          "quantidade": 141,
          "produtos": 141
        },
        "2025-09": {
          "faturamento": 19787.520000000022,
          "quantidade": 122,
          "produtos": 122
        },
        "2025-10": {
          "faturamento": 28918.440000000042,
          "quantidade": 144,
          "produtos": 144
        },
        "2025-11": {
          "faturamento": 93486.87999999986,
          "quantidade": 237,
          "produtos": 237
        },
        "2025-12": {
          "faturamento": 93049.24999999977,
          "quantidade": 221,
          "produtos": 221
        },
        "2026-01": {
          "faturamento": 74118.74999999987,
          "quantidade": 166,
          "produtos": 166
        },
        "2026-02": {
          "faturamento": 22721.31000000004,
          "quantidade": 106,
          "produtos": 106
        },
        "2024-04": {
          "faturamento": 0,
          "quantidade": 0,
          "produtos": 0
        },
        "2024-05": {
          "faturamento": 0,
          "quantidade": 0,
          "produtos": 0
        }
      }
    },
    {
      "loja_id": 20,
      "analises": {
        "2024-11": {
          "faturamento": 3445.200000000001,
          "quantidade": 28,
          "produtos": 28
        },
        "2024-12": {
          "faturamento": 2214.4000000000005,
          "quantidade": 14,
          "produtos": 14
        },
        "2025-03": {
          "faturamento": 12367.599999999993,
          "quantidade": 50,
          "produtos": 50
        },
        "2025-04": {
          "faturamento": 27960.400000000005,
          "quantidade": 56,
          "produtos": 56
        },
        "2025-05": {
          "faturamento": 32014.399999999994,
          "quantidade": 54,
          "produtos": 54
        },
        "2025-06": {
          "faturamento": 39084.20000000002,
          "quantidade": 70,
          "produtos": 70
        },
        "2025-07": {
          "faturamento": 43265.90000000004,
          "quantidade": 59,
          "produtos": 59
        },
        "2025-08": {
          "faturamento": 41758.70000000001,
          "quantidade": 55,
          "produtos": 55
        },
        "2025-09": {
          "faturamento": 23871.300000000003,
          "quantidade": 59,
          "produtos": 59
        },
        "2025-10": {
          "faturamento": 21148.550000000003,
          "quantidade": 46,
          "produtos": 46
        },
        "2025-11": {
          "faturamento": 28033.570000000003,
          "quantidade": 48,
          "produtos": 48
        },
        "2025-12": {
          "faturamento": 31050.250000000007,
          "quantidade": 52,
          "produtos": 52
        },
        "2026-01": {
          "faturamento": 29374.590000000004,
          "quantidade": 53,
          "produtos": 53
        },
        "2026-02": {
          "faturamento": 7359.899999999998,
          "quantidade": 30,
          "produtos": 30
        },
        "2025-02": {
          "faturamento": 0,
          "quantidade": 0,
          "produtos": 0
        }
      }
    },
    {
      "loja_id": 3,
      "analises": {
        "2025-12": {
          "faturamento": 60625.00000000003,
          "quantidade": 153,
          "produtos": 153
        },
        "2026-01": {
          "faturamento": 17534.010000000017,
          "quantidade": 118,
          "produtos": 118
        },
        "2026-02": {
          "faturamento": 9193.919999999991,
          "quantidade": 75,
          "produtos": 75
        },
        "2025-02": {
          "faturamento": 0,
          "quantidade": 0,
          "produtos": 0
        }
      }
    },
    {
      "loja_id": 4,
      "analises": {
        "2024-06": {
          "faturamento": 2428.800000000002,
          "quantidade": 30,
          "produtos": 30
        },
        "2024-07": {
          "faturamento": 3576.230000000003,
          "quantidade": 63,
          "produtos": 63
        },
        "2024-08": {
          "faturamento": 3337.600000000002,
          "quantidade": 51,
          "produtos": 51
        },
        "2024-09": {
          "faturamento": 3598.5400000000027,
          "quantidade": 53,
          "produtos": 53
        },
        "2024-10": {
          "faturamento": 4201.620000000002,
          "quantidade": 55,
          "produtos": 55
        },
        "2024-11": {
          "faturamento": 6108.259999999993,
          "quantidade": 69,
          "produtos": 69
        },
        "2024-12": {
          "faturamento": 7533.839999999993,
          "quantidade": 73,
          "produtos": 73
        },
        "2025-01": {
          "faturamento": 5191.599999999996,
          "quantidade": 48,
          "produtos": 48
        },
        "2025-02": {
          "faturamento": 4289.289999999999,
          "quantidade": 55,
          "produtos": 55
        },
        "2025-03": {
          "faturamento": 3634.620000000002,
          "quantidade": 51,
          "produtos": 51
        },
        "2025-04": {
          "faturamento": 3770.820000000002,
          "quantidade": 38,
          "produtos": 38
        },
        "2025-05": {
          "faturamento": 3522.080000000004,
          "quantidade": 56,
          "produtos": 56
        },
        "2025-06": {
          "faturamento": 4652.609999999995,
          "quantidade": 54,
          "produtos": 54
        },
        "2025-07": {
          "faturamento": 4613.049999999995,
          "quantidade": 57,
          "produtos": 57
        },
        "2025-08": {
          "faturamento": 5288.209999999994,
          "quantidade": 57,
          "produtos": 57
        },
        "2025-09": {
          "faturamento": 4277.869999999994,
          "quantidade": 50,
          "produtos": 50
        },
        "2025-10": {
          "faturamento": 4157.700000000002,
          "quantidade": 57,
          "produtos": 57
        },
        "2025-11": {
          "faturamento": 8847.099999999986,
          "quantidade": 74,
          "produtos": 74
        },
        "2025-12": {
          "faturamento": 6414.009999999991,
          "quantidade": 69,
          "produtos": 69
        },
        "2026-01": {
          "faturamento": 4609.9099999999935,
          "quantidade": 66,
          "produtos": 66
        },
        "2026-02": {
          "faturamento": 823.1999999999996,
          "quantidade": 20,
          "produtos": 20
        },
        "2023-05": {
          "faturamento": 0,
          "quantidade": 0,
          "produtos": 0
        },
        "2023-06": {
          "faturamento": 0,
          "quantidade": 0,
          "produtos": 0
        },
        "2023-07": {
          "faturamento": 0,
          "quantidade": 0,
          "produtos": 0
        },
        "2023-08": {
          "faturamento": 0,
          "quantidade": 0,
          "produtos": 0
        },
        "2023-09": {
          "faturamento": 0,
          "quantidade": 0,
          "produtos": 0
        },
        "2023-10": {
          "faturamento": 0,
          "quantidade": 0,
          "produtos": 0
        },
        "2023-11": {
          "faturamento": 0,
          "quantidade": 0,
          "produtos": 0
        },
        "2023-12": {
          "faturamento": 0,
          "quantidade": 0,
          "produtos": 0
        },
        "2024-01": {
          "faturamento": 0,
          "quantidade": 0,
          "produtos": 0
        },
        "2024-02": {
          "faturamento": 0,
          "quantidade": 0,
          "produtos": 0
        },
        "2024-03": {
          "faturamento": 0,
          "quantidade": 0,
          "produtos": 0
        },
        "2024-04": {
          "faturamento": 0,
          "quantidade": 0,
          "produtos": 0
        },
        "2024-05": {
          "faturamento": 0,
          "quantidade": 0,
          "produtos": 0
        }
      }
    },
    {
      "loja_id": 5,
      "analises": {
        "2024-06": {
          "faturamento": 12191.899999999998,
          "quantidade": 81,
          "produtos": 81
        },
        "2024-07": {
          "faturamento": 18438.720000000016,
          "quantidade": 99,
          "produtos": 99
        },
        "2024-08": {
          "faturamento": 18413.050000000003,
          "quantidade": 95,
          "produtos": 95
        },
        "2024-09": {
          "faturamento": 23064.55000000002,
          "quantidade": 117,
          "produtos": 117
        },
        "2024-10": {
          "faturamento": 22697.48000000002,
          "quantidade": 117,
          "produtos": 117
        },
        "2024-11": {
          "faturamento": 28308.55000000001,
          "quantidade": 124,
          "produtos": 124
        },
        "2024-12": {
          "faturamento": 34296.180000000044,
          "quantidade": 118,
          "produtos": 118
        },
        "2025-01": {
          "faturamento": 25539.930000000008,
          "quantidade": 99,
          "produtos": 99
        },
        "2025-02": {
          "faturamento": 20648.38,
          "quantidade": 91,
          "produtos": 91
        },
        "2025-03": {
          "faturamento": 24436.429999999997,
          "quantidade": 103,
          "produtos": 103
        },
        "2025-04": {
          "faturamento": 26859.01000000002,
          "quantidade": 94,
          "produtos": 94
        },
        "2025-05": {
          "faturamento": 29147.430000000004,
          "quantidade": 92,
          "produtos": 92
        },
        "2025-06": {
          "faturamento": 24523.300000000025,
          "quantidade": 101,
          "produtos": 101
        },
        "2025-07": {
          "faturamento": 31505.03000000003,
          "quantidade": 127,
          "produtos": 127
        },
        "2025-08": {
          "faturamento": 37111.400000000074,
          "quantidade": 147,
          "produtos": 147
        },
        "2025-09": {
          "faturamento": 39533.91000000006,
          "quantidade": 134,
          "produtos": 134
        },
        "2025-10": {
          "faturamento": 46715.100000000064,
          "quantidade": 133,
          "produtos": 133
        },
        "2025-11": {
          "faturamento": 53759.70000000003,
          "quantidade": 160,
          "produtos": 160
        },
        "2025-12": {
          "faturamento": 50170.60000000003,
          "quantidade": 85,
          "produtos": 85
        },
        "2026-01": {
          "faturamento": 43523.95000000002,
          "quantidade": 84,
          "produtos": 84
        },
        "2026-02": {
          "faturamento": 13699.229999999996,
          "quantidade": 77,
          "produtos": 77
        }
      }
    },
    {
      "loja_id": 6,
      "analises": {
        "2024-06": {
          "faturamento": 21495.170000000013,
          "quantidade": 41,
          "produtos": 41
        },
        "2024-07": {
          "faturamento": 29445.089999999997,
          "quantidade": 38,
          "produtos": 38
        },
        "2024-08": {
          "faturamento": 32663.190000000002,
          "quantidade": 41,
          "produtos": 41
        },
        "2024-09": {
          "faturamento": 26209.660000000003,
          "quantidade": 38,
          "produtos": 38
        },
        "2024-10": {
          "faturamento": 36194.62,
          "quantidade": 40,
          "produtos": 40
        },
        "2024-11": {
          "faturamento": 39196.83000000002,
          "quantidade": 47,
          "produtos": 47
        },
        "2024-12": {
          "faturamento": 34967.000000000015,
          "quantidade": 39,
          "produtos": 39
        },
        "2025-01": {
          "faturamento": 49266.04000000001,
          "quantidade": 41,
          "produtos": 41
        },
        "2025-02": {
          "faturamento": 68289.3,
          "quantidade": 40,
          "produtos": 40
        },
        "2025-03": {
          "faturamento": 58878.90999999998,
          "quantidade": 39,
          "produtos": 39
        },
        "2025-04": {
          "faturamento": 44559.609999999986,
          "quantidade": 40,
          "produtos": 40
        },
        "2025-05": {
          "faturamento": 56290.36000000001,
          "quantidade": 39,
          "produtos": 39
        },
        "2025-06": {
          "faturamento": 62345.14000000001,
          "quantidade": 62,
          "produtos": 62
        },
        "2025-07": {
          "faturamento": 70996.22000000003,
          "quantidade": 53,
          "produtos": 53
        },
        "2025-08": {
          "faturamento": 80747.43999999996,
          "quantidade": 55,
          "produtos": 55
        },
        "2025-09": {
          "faturamento": 61601.820000000014,
          "quantidade": 51,
          "produtos": 51
        },
        "2025-10": {
          "faturamento": 79793.51999999997,
          "quantidade": 49,
          "produtos": 49
        },
        "2025-11": {
          "faturamento": 72020.25999999997,
          "quantidade": 43,
          "produtos": 43
        },
        "2025-12": {
          "faturamento": 78167.97999999997,
          "quantidade": 41,
          "produtos": 41
        },
        "2026-01": {
          "faturamento": 100178.0099999999,
          "quantidade": 136,
          "produtos": 136
        },
        "2026-02": {
          "faturamento": 44034.560000000034,
          "quantidade": 108,
          "produtos": 108
        },
        "2023-06": {
          "faturamento": 0,
          "quantidade": 0,
          "produtos": 0
        },
        "2023-10": {
          "faturamento": 0,
          "quantidade": 0,
          "produtos": 0
        }
      }
    },
    {
      "loja_id": 7,
      "analises": {
        "2025-09": {
          "faturamento": 89.9,
          "quantidade": 1,
          "produtos": 1
        },
        "2025-10": {
          "faturamento": 4900.849999999997,
          "quantidade": 36,
          "produtos": 36
        },
        "2025-11": {
          "faturamento": 4732.5999999999985,
          "quantidade": 28,
          "produtos": 28
        },
        "2025-12": {
          "faturamento": 4093.95,
          "quantidade": 25,
          "produtos": 25
        },
        "2026-01": {
          "faturamento": 4511.199999999998,
          "quantidade": 21,
          "produtos": 21
        },
        "2026-02": {
          "faturamento": 549.1999999999999,
          "quantidade": 10,
          "produtos": 10
        },
        "2025-02": {
          "faturamento": 0,
          "quantidade": 0,
          "produtos": 0
        }
      }
    },
    {
      "loja_id": 8,
      "analises": {
        "2024-06": {
          "faturamento": 9743.699999999992,
          "quantidade": 29,
          "produtos": 29
        },
        "2024-07": {
          "faturamento": 8245.699999999993,
          "quantidade": 34,
          "produtos": 34
        },
        "2024-08": {
          "faturamento": 7086.899999999993,
          "quantidade": 30,
          "produtos": 30
        },
        "2024-09": {
          "faturamento": 8076.999999999998,
          "quantidade": 31,
          "produtos": 31
        },
        "2024-10": {
          "faturamento": 10867.299999999997,
          "quantidade": 41,
          "produtos": 41
        },
        "2024-11": {
          "faturamento": 6857.499999999995,
          "quantidade": 29,
          "produtos": 29
        },
        "2024-12": {
          "faturamento": 1283.1000000000001,
          "quantidade": 6,
          "produtos": 6
        },
        "2025-01": {
          "faturamento": 5142.499999999998,
          "quantidade": 25,
          "produtos": 25
        },
        "2025-02": {
          "faturamento": 6468.799999999998,
          "quantidade": 24,
          "produtos": 24
        },
        "2025-03": {
          "faturamento": 5299.999999999998,
          "quantidade": 22,
          "produtos": 22
        },
        "2025-04": {
          "faturamento": 6601.499999999997,
          "quantidade": 31,
          "produtos": 31
        },
        "2025-05": {
          "faturamento": 6798.899999999996,
          "quantidade": 29,
          "produtos": 29
        },
        "2025-06": {
          "faturamento": 6055.599999999996,
          "quantidade": 27,
          "produtos": 27
        },
        "2025-07": {
          "faturamento": 4224.3,
          "quantidade": 25,
          "produtos": 25
        },
        "2025-08": {
          "faturamento": 3421.4000000000015,
          "quantidade": 24,
          "produtos": 24
        },
        "2025-09": {
          "faturamento": 2698.8000000000006,
          "quantidade": 14,
          "produtos": 14
        },
        "2025-10": {
          "faturamento": 3888.1000000000017,
          "quantidade": 26,
          "produtos": 26
        },
        "2025-11": {
          "faturamento": 6483.499999999998,
          "quantidade": 24,
          "produtos": 24
        },
        "2025-12": {
          "faturamento": 137134.44999999978,
          "quantidade": 189,
          "produtos": 189
        },
        "2026-01": {
          "faturamento": 99661.53999999992,
          "quantidade": 161,
          "produtos": 161
        },
        "2026-02": {
          "faturamento": 35879.35000000004,
          "quantidade": 119,
          "produtos": 119
        }
      }
    },
    {
      "loja_id": 9,
      "analises": {
        "2024-06": {
          "faturamento": 121788.38,
          "quantidade": 281,
          "produtos": 281
        },
        "2024-07": {
          "faturamento": 140036.2399999998,
          "quantidade": 293,
          "produtos": 293
        },
        "2024-08": {
          "faturamento": 169342.7499999998,
          "quantidade": 309,
          "produtos": 309
        },
        "2024-09": {
          "faturamento": 160222.72999999995,
          "quantidade": 302,
          "produtos": 302
        },
        "2024-10": {
          "faturamento": 165114.77999999974,
          "quantidade": 303,
          "produtos": 303
        },
        "2024-11": {
          "faturamento": 177876.30999999988,
          "quantidade": 304,
          "produtos": 304
        },
        "2024-12": {
          "faturamento": 236417.55999999962,
          "quantidade": 314,
          "produtos": 314
        },
        "2025-01": {
          "faturamento": 173360.68000000002,
          "quantidade": 299,
          "produtos": 299
        },
        "2025-02": {
          "faturamento": 178566.39999999964,
          "quantidade": 304,
          "produtos": 304
        },
        "2025-03": {
          "faturamento": 197549.22999999975,
          "quantidade": 306,
          "produtos": 306
        },
        "2025-04": {
          "faturamento": 178294.53999999995,
          "quantidade": 299,
          "produtos": 299
        },
        "2025-05": {
          "faturamento": 216447.08999999982,
          "quantidade": 311,
          "produtos": 311
        },
        "2025-06": {
          "faturamento": 217562.50999999986,
          "quantidade": 297,
          "produtos": 297
        },
        "2025-07": {
          "faturamento": 201337.18000000008,
          "quantidade": 304,
          "produtos": 304
        },
        "2025-08": {
          "faturamento": 247804.30999999974,
          "quantidade": 317,
          "produtos": 317
        },
        "2025-09": {
          "faturamento": 199166.64999999982,
          "quantidade": 316,
          "produtos": 316
        },
        "2025-10": {
          "faturamento": 196864.21999999983,
          "quantidade": 308,
          "produtos": 308
        },
        "2025-11": {
          "faturamento": 162843.2499999997,
          "quantidade": 271,
          "produtos": 271
        },
        "2025-12": {
          "faturamento": 28649.650000000016,
          "quantidade": 107,
          "produtos": 107
        },
        "2023-05": {
          "faturamento": 0,
          "quantidade": 0,
          "produtos": 0
        },
        "2023-06": {
          "faturamento": 0,
          "quantidade": 0,
          "produtos": 0
        },
        "2023-07": {
          "faturamento": 0,
          "quantidade": 0,
          "produtos": 0
        },
        "2023-08": {
          "faturamento": 0,
          "quantidade": 0,
          "produtos": 0
        },
        "2023-09": {
          "faturamento": 0,
          "quantidade": 0,
          "produtos": 0
        },
        "2023-10": {
          "faturamento": 0,
          "quantidade": 0,
          "produtos": 0
        },
        "2023-11": {
          "faturamento": 0,
          "quantidade": 0,
          "produtos": 0
        },
        "2023-12": {
          "faturamento": 0,
          "quantidade": 0,
          "produtos": 0
        },
        "2024-01": {
          "faturamento": 0,
          "quantidade": 0,
          "produtos": 0
        },
        "2024-02": {
          "faturamento": 0,
          "quantidade": 0,
          "produtos": 0
        },
        "2024-03": {
          "faturamento": 0,
          "quantidade": 0,
          "produtos": 0
        },
        "2024-04": {
          "faturamento": 0,
          "quantidade": 0,
          "produtos": 0
        },
        "2024-05": {
          "faturamento": 0,
          "quantidade": 0,
          "produtos": 0
        }
      }
    }
  ]
}